parsemon/json.py
parsemon/sourcemap.py
parsemon/parser.py
parsemon/validator.py
parsemon/stream.py
parsemon/extensions.cpython-38-x86_64-linux-gnu.so
parsemon/coroutine.py
parsemon/basic.py
parsemon/__init__.py
parsemon/error.py
parsemon/__pycache__/json.cpython-38.pyc
parsemon/__pycache__/coroutine.cpython-38.pyc
parsemon/__pycache__/validator.cpython-38.pyc
parsemon/__pycache__/basic.cpython-38.pyc
parsemon/__pycache__/error.cpython-38.pyc
parsemon/__pycache__/__init__.cpython-38.pyc
parsemon/__pycache__/stream.cpython-38.pyc
parsemon/__pycache__/parser.cpython-38.pyc
parsemon/__pycache__/sourcemap.cpython-38.pyc
parsemon/internals/parser.py
parsemon/internals/primitives.py
parsemon/internals/__init__.py
parsemon/internals/__pycache__/primitives.cpython-38.pyc
parsemon/internals/__pycache__/__init__.cpython-38.pyc
parsemon/internals/__pycache__/parser.cpython-38.pyc
parsemon2-3.2.2.dist-info/WHEEL
parsemon2-3.2.2.dist-info/top_level.txt
parsemon2-3.2.2.dist-info/RECORD
parsemon2-3.2.2.dist-info/METADATA
parsemon2-3.2.2.dist-info/LICENSE
