Metadata-Version: 2.1
Name: parsemon2
Version: 3.2.2
Summary: A monadic parsing toolset for python
Home-page: UNKNOWN
Author: Sebastian Jordan
Author-email: sebastian.jordan.mail@googlemail.com
License: GPLv3
Platform: UNKNOWN
